AUTHORS
LICENSE
MANIFEST.in
README
setup.py
django_lean/__init__.py
django_lean/lockfile.py
django_lean/utils.py
django_lean.egg-info/PKG-INFO
django_lean.egg-info/SOURCES.txt
django_lean.egg-info/dependency_links.txt
django_lean.egg-info/requires.txt
django_lean.egg-info/top_level.txt
django_lean/experiments/__init__.py
django_lean/experiments/admin.py
django_lean/experiments/admin_urls.py
django_lean/experiments/loader.py
django_lean/experiments/models.py
django_lean/experiments/reports.py
django_lean/experiments/signals.py
django_lean/experiments/significance.py
django_lean/experiments/stats.py
django_lean/experiments/testsettings.py
django_lean/experiments/urls.py
django_lean/experiments/utils.py
django_lean/experiments/views.py
django_lean/experiments/management/__init__.py
django_lean/experiments/management/commands/__init__.py
django_lean/experiments/management/commands/update_experiment_reports.py
django_lean/experiments/migrations/0001_initial.py
django_lean/experiments/migrations/0002_anonymous_visitors_and_goals.py
django_lean/experiments/migrations/0003_define_goal_types.py
django_lean/experiments/migrations/0004_add_group_size_to_activity_reports.py
django_lean/experiments/migrations/0005_add_confidence_to_activity_reports.py
django_lean/experiments/migrations/0006_rename_daily_activity_model.py
django_lean/experiments/migrations/0007_add_daily_conversion_report_and_goal_data.py
django_lean/experiments/migrations/0008_add_indices.py
django_lean/experiments/migrations/0009_rename_activity_to_engagement.py
django_lean/experiments/migrations/__init__.py
django_lean/experiments/templates/experiments/confidence_value.html
django_lean/experiments/templates/experiments/conversion_details.html
django_lean/experiments/templates/experiments/conversion_summary.html
django_lean/experiments/templates/experiments/engagement_details.html
django_lean/experiments/templates/experiments/engagement_summary.html
django_lean/experiments/templates/experiments/experiment_details.html
django_lean/experiments/templates/experiments/improvement_value.html
django_lean/experiments/templates/experiments/list_experiments.html
