Metadata-Version: 1.0
Name: django-lean
Version: 0.12
Summary: A framework for performing and analyzing split-test experiments in Django applications.
Home-page: http://bitbucket.org/akoha/django-lean/wiki/Home
Author: Akoha, Inc.
Author-email: django-lean@akoha.com
License: BSD
Platform: any
Classifier: Development Status :: 4 - Beta
Classifier: Environment :: Web Environment
Classifier: Framework :: Django
Classifier: Intended Audience :: Developers
Classifier: License :: OSI Approved :: BSD License
Classifier: Operating System :: OS Independent
Classifier: Programming Language :: Python
Classifier: Topic :: Software Development :: Libraries :: Python Modules
